{
    "projectile": {
        "170": {
            "components": {
                "camp": {
                    "role_id": 32
                }, 
                "display": {
                    "real_scale": [
                        2.0, 
                        2.0, 
                        2.0
                    ]
                }, 
                "movement": {
                    "pitch": {
                        "__tuple__": true, 
                        "items": [
                            0, 
                            0
                        ]
                    }, 
                    "position": {
                        "__tuple__": true, 
                        "items": [
                            [
                                -58, 
                                3470278656
                            ], 
                            [
                                0, 
                                0
                            ], 
                            [
                                10, 
                                1473163264
                            ]
                        ]
                    }, 
                    "roll": {
                        "__tuple__": true, 
                        "items": [
                            0, 
                            0
                        ]
                    }, 
                    "yaw": {
                        "__tuple__": true, 
                        "items": [
                            0, 
                            0
                        ]
                    }
                }
            }, 
            "entity_id": 134247451, 
            "name": "\u7d2b\u8272\u589e\u76ca", 
            "type": 64, 
            "unit_id": 170
        }, 
        "171": {
            "components": {
                "camp": {
                    "role_id": 32
                }, 
                "display": {
                    "real_scale": [
                        2.0, 
                        2.0, 
                        2.0
                    ]
                }, 
                "movement": {
                    "pitch": {
                        "__tuple__": true, 
                        "items": [
                            0, 
                            0
                        ]
                    }, 
                    "position": {
                        "__tuple__": true, 
                        "items": [
                            [
                                -56, 
                                3018522624
                            ], 
                            [
                                0, 
                                0
                            ], 
                            [
                                14, 
                                4044881920
                            ]
                        ]
                    }, 
                    "roll": {
                        "__tuple__": true, 
                        "items": [
                            0, 
                            0
                        ]
                    }, 
                    "yaw": {
                        "__tuple__": true, 
                        "items": [
                            0, 
                            0
                        ]
                    }
                }
            }, 
            "entity_id": 134247451, 
            "name": "\u7d2b\u8272\u589e\u76ca", 
            "type": 64, 
            "unit_id": 171
        }, 
        "172": {
            "components": {
                "camp": {
                    "role_id": 32
                }, 
                "display": {
                    "real_scale": [
                        2.0, 
                        2.0, 
                        2.0
                    ]
                }, 
                "movement": {
                    "pitch": {
                        "__tuple__": true, 
                        "items": [
                            0, 
                            0
                        ]
                    }, 
                    "position": {
                        "__tuple__": true, 
                        "items": [
                            [
                                -57, 
                                2153857024
                            ], 
                            [
                                0, 
                                0
                            ], 
                            [
                                56, 
                                1791639552
                            ]
                        ]
                    }, 
                    "roll": {
                        "__tuple__": true, 
                        "items": [
                            0, 
                            0
                        ]
                    }, 
                    "yaw": {
                        "__tuple__": true, 
                        "items": [
                            0, 
                            0
                        ]
                    }
                }
            }, 
            "entity_id": 134247451, 
            "name": "\u7d2b\u8272\u589e\u76ca", 
            "type": 64, 
            "unit_id": 172
        }, 
        "174": {
            "components": {
                "camp": {
                    "role_id": 32
                }, 
                "display": {
                    "real_scale": [
                        1.0, 
                        1.0, 
                        1.0
                    ]
                }, 
                "movement": {
                    "pitch": {
                        "__tuple__": true, 
                        "items": [
                            0, 
                            0
                        ]
                    }, 
                    "position": {
                        "__tuple__": true, 
                        "items": [
                            [
                                11, 
                                3381575680
                            ], 
                            [
                                0, 
                                1986955904
                            ], 
                            [
                                9, 
                                3235831808
                            ]
                        ]
                    }, 
                    "roll": {
                        "__tuple__": true, 
                        "items": [
                            0, 
                            0
                        ]
                    }, 
                    "yaw": {
                        "__tuple__": true, 
                        "items": [
                            0, 
                            0
                        ]
                    }
                }
            }, 
            "entity_id": 134247451, 
            "name": "\u7d2b\u8272\u589e\u76ca", 
            "type": 64, 
            "unit_id": 174
        }, 
        "175": {
            "components": {
                "camp": {
                    "role_id": 32
                }, 
                "display": {
                    "real_scale": [
                        2.0, 
                        2.0, 
                        2.0
                    ]
                }, 
                "movement": {
                    "pitch": {
                        "__tuple__": true, 
                        "items": [
                            0, 
                            0
                        ]
                    }, 
                    "position": {
                        "__tuple__": true, 
                        "items": [
                            [
                                10, 
                                2225045504
                            ], 
                            [
                                0, 
                                2471238144
                            ], 
                            [
                                9, 
                                1025097728
                            ]
                        ]
                    }, 
                    "roll": {
                        "__tuple__": true, 
                        "items": [
                            0, 
                            0
                        ]
                    }, 
                    "yaw": {
                        "__tuple__": true, 
                        "items": [
                            0, 
                            0
                        ]
                    }
                }
            }, 
            "entity_id": 134247451, 
            "name": "\u7d2b\u8272\u589e\u76ca", 
            "type": 64, 
            "unit_id": 175
        }, 
        "176": {
            "components": {
                "camp": {
                    "role_id": 32
                }, 
                "display": {
                    "real_scale": [
                        2.0, 
                        2.0, 
                        2.0
                    ]
                }, 
                "movement": {
                    "pitch": {
                        "__tuple__": true, 
                        "items": [
                            0, 
                            0
                        ]
                    }, 
                    "position": {
                        "__tuple__": true, 
                        "items": [
                            [
                                9, 
                                1629646848
                            ], 
                            [
                                0, 
                                2929715456
                            ], 
                            [
                                8, 
                                765231104
                            ]
                        ]
                    }, 
                    "roll": {
                        "__tuple__": true, 
                        "items": [
                            0, 
                            0
                        ]
                    }, 
                    "yaw": {
                        "__tuple__": true, 
                        "items": [
                            0, 
                            0
                        ]
                    }
                }
            }, 
            "entity_id": 134247451, 
            "name": "\u7d2b\u8272\u589e\u76ca", 
            "type": 64, 
            "unit_id": 176
        }, 
        "177": {
            "components": {
                "camp": {
                    "role_id": 32
                }, 
                "display": {
                    "real_scale": [
                        2.0, 
                        2.0, 
                        2.0
                    ]
                }, 
                "movement": {
                    "pitch": {
                        "__tuple__": true, 
                        "items": [
                            0, 
                            0
                        ]
                    }, 
                    "position": {
                        "__tuple__": true, 
                        "items": [
                            [
                                8, 
                                3015938048
                            ], 
                            [
                                0, 
                                3050396160
                            ], 
                            [
                                6, 
                                2614636544
                            ]
                        ]
                    }, 
                    "roll": {
                        "__tuple__": true, 
                        "items": [
                            0, 
                            0
                        ]
                    }, 
                    "yaw": {
                        "__tuple__": true, 
                        "items": [
                            0, 
                            0
                        ]
                    }
                }
            }, 
            "entity_id": 134247451, 
            "name": "\u7d2b\u8272\u589e\u76ca", 
            "type": 64, 
            "unit_id": 177
        }, 
        "178": {
            "components": {
                "camp": {
                    "role_id": 32
                }, 
                "display": {
                    "real_scale": [
                        2.0, 
                        2.0, 
                        2.0
                    ]
                }, 
                "movement": {
                    "pitch": {
                        "__tuple__": true, 
                        "items": [
                            0, 
                            0
                        ]
                    }, 
                    "position": {
                        "__tuple__": true, 
                        "items": [
                            [
                                8, 
                                1218535424
                            ], 
                            [
                                0, 
                                3052581632
                            ], 
                            [
                                5, 
                                2784200704
                            ]
                        ]
                    }, 
                    "roll": {
                        "__tuple__": true, 
                        "items": [
                            0, 
                            0
                        ]
                    }, 
                    "yaw": {
                        "__tuple__": true, 
                        "items": [
                            0, 
                            0
                        ]
                    }
                }
            }, 
            "entity_id": 134247451, 
            "name": "\u7d2b\u8272\u589e\u76ca", 
            "type": 64, 
            "unit_id": 178
        }, 
        "179": {
            "components": {
                "camp": {
                    "role_id": 32
                }, 
                "display": {
                    "real_scale": [
                        2.0, 
                        2.0, 
                        2.0
                    ]
                }, 
                "movement": {
                    "pitch": {
                        "__tuple__": true, 
                        "items": [
                            0, 
                            0
                        ]
                    }, 
                    "position": {
                        "__tuple__": true, 
                        "items": [
                            [
                                7, 
                                4080373760
                            ], 
                            [
                                0, 
                                3001713408
                            ], 
                            [
                                4, 
                                2223626240
                            ]
                        ]
                    }, 
                    "roll": {
                        "__tuple__": true, 
                        "items": [
                            0, 
                            0
                        ]
                    }, 
                    "yaw": {
                        "__tuple__": true, 
                        "items": [
                            0, 
                            0
                        ]
                    }
                }
            }, 
            "entity_id": 134247451, 
            "name": "\u7d2b\u8272\u589e\u76ca", 
            "type": 64, 
            "unit_id": 179
        }, 
        "180": {
            "components": {
                "camp": {
                    "role_id": 32
                }, 
                "display": {
                    "real_scale": [
                        2.0, 
                        2.0, 
                        2.0
                    ]
                }, 
                "movement": {
                    "pitch": {
                        "__tuple__": true, 
                        "items": [
                            0, 
                            0
                        ]
                    }, 
                    "position": {
                        "__tuple__": true, 
                        "items": [
                            [
                                7, 
                                4010209280
                            ], 
                            [
                                0, 
                                2992730368
                            ], 
                            [
                                3, 
                                2075244544
                            ]
                        ]
                    }, 
                    "roll": {
                        "__tuple__": true, 
                        "items": [
                            0, 
                            0
                        ]
                    }, 
                    "yaw": {
                        "__tuple__": true, 
                        "items": [
                            0, 
                            0
                        ]
                    }
                }
            }, 
            "entity_id": 134247451, 
            "name": "\u7d2b\u8272\u589e\u76ca", 
            "type": 64, 
            "unit_id": 180
        }, 
        "181": {
            "components": {
                "camp": {
                    "role_id": 32
                }, 
                "display": {
                    "real_scale": [
                        2.0, 
                        2.0, 
                        2.0
                    ]
                }, 
                "movement": {
                    "pitch": {
                        "__tuple__": true, 
                        "items": [
                            0, 
                            0
                        ]
                    }, 
                    "position": {
                        "__tuple__": true, 
                        "items": [
                            [
                                8, 
                                792522752
                            ], 
                            [
                                0, 
                                2993294080
                            ], 
                            [
                                2, 
                                1936041984
                            ]
                        ]
                    }, 
                    "roll": {
                        "__tuple__": true, 
                        "items": [
                            0, 
                            0
                        ]
                    }, 
                    "yaw": {
                        "__tuple__": true, 
                        "items": [
                            0, 
                            0
                        ]
                    }
                }
            }, 
            "entity_id": 134247451, 
            "name": "\u7d2b\u8272\u589e\u76ca", 
            "type": 64, 
            "unit_id": 181
        }, 
        "182": {
            "components": {
                "camp": {
                    "role_id": 32
                }, 
                "display": {
                    "real_scale": [
                        2.0, 
                        2.0, 
                        2.0
                    ]
                }, 
                "movement": {
                    "pitch": {
                        "__tuple__": true, 
                        "items": [
                            0, 
                            0
                        ]
                    }, 
                    "position": {
                        "__tuple__": true, 
                        "items": [
                            [
                                8, 
                                4046221312
                            ], 
                            [
                                0, 
                                2815506432
                            ], 
                            [
                                1, 
                                691111936
                            ]
                        ]
                    }, 
                    "roll": {
                        "__tuple__": true, 
                        "items": [
                            0, 
                            0
                        ]
                    }, 
                    "yaw": {
                        "__tuple__": true, 
                        "items": [
                            0, 
                            0
                        ]
                    }
                }
            }, 
            "entity_id": 134247451, 
            "name": "\u7d2b\u8272\u589e\u76ca", 
            "type": 64, 
            "unit_id": 182
        }, 
        "183": {
            "components": {
                "camp": {
                    "role_id": 32
                }, 
                "display": {
                    "real_scale": [
                        2.0, 
                        2.0, 
                        2.0
                    ]
                }, 
                "movement": {
                    "pitch": {
                        "__tuple__": true, 
                        "items": [
                            0, 
                            0
                        ]
                    }, 
                    "position": {
                        "__tuple__": true, 
                        "items": [
                            [
                                9, 
                                3109847040
                            ], 
                            [
                                0, 
                                2521554176
                            ], 
                            [
                                0, 
                                1401825280
                            ]
                        ]
                    }, 
                    "roll": {
                        "__tuple__": true, 
                        "items": [
                            0, 
                            0
                        ]
                    }, 
                    "yaw": {
                        "__tuple__": true, 
                        "items": [
                            0, 
                            0
                        ]
                    }
                }
            }, 
            "entity_id": 134247451, 
            "name": "\u7d2b\u8272\u589e\u76ca", 
            "type": 64, 
            "unit_id": 183
        }, 
        "184": {
            "components": {
                "camp": {
                    "role_id": 32
                }, 
                "display": {
                    "real_scale": [
                        2.0, 
                        2.0, 
                        2.0
                    ]
                }, 
                "movement": {
                    "pitch": {
                        "__tuple__": true, 
                        "items": [
                            0, 
                            0
                        ]
                    }, 
                    "position": {
                        "__tuple__": true, 
                        "items": [
                            [
                                10, 
                                3704315904
                            ], 
                            [
                                0, 
                                2250295296
                            ], 
                            [
                                -1, 
                                3946543104
                            ]
                        ]
                    }, 
                    "roll": {
                        "__tuple__": true, 
                        "items": [
                            0, 
                            0
                        ]
                    }, 
                    "yaw": {
                        "__tuple__": true, 
                        "items": [
                            0, 
                            0
                        ]
                    }
                }
            }, 
            "entity_id": 134247451, 
            "name": "\u7d2b\u8272\u589e\u76ca", 
            "type": 64, 
            "unit_id": 184
        }, 
        "185": {
            "components": {
                "camp": {
                    "role_id": 32
                }, 
                "display": {
                    "real_scale": [
                        2.0, 
                        2.0, 
                        2.0
                    ]
                }, 
                "movement": {
                    "pitch": {
                        "__tuple__": true, 
                        "items": [
                            0, 
                            0
                        ]
                    }, 
                    "position": {
                        "__tuple__": true, 
                        "items": [
                            [
                                11, 
                                3639558144
                            ], 
                            [
                                0, 
                                1882488576
                            ], 
                            [
                                -1, 
                                3128313856
                            ]
                        ]
                    }, 
                    "roll": {
                        "__tuple__": true, 
                        "items": [
                            0, 
                            0
                        ]
                    }, 
                    "yaw": {
                        "__tuple__": true, 
                        "items": [
                            0, 
                            0
                        ]
                    }
                }
            }, 
            "entity_id": 134247451, 
            "name": "\u7d2b\u8272\u589e\u76ca", 
            "type": 64, 
            "unit_id": 185
        }, 
        "186": {
            "components": {
                "camp": {
                    "role_id": 32
                }, 
                "display": {
                    "real_scale": [
                        2.0, 
                        2.0, 
                        2.0
                    ]
                }, 
                "movement": {
                    "pitch": {
                        "__tuple__": true, 
                        "items": [
                            0, 
                            0
                        ]
                    }, 
                    "position": {
                        "__tuple__": true, 
                        "items": [
                            [
                                12, 
                                4164984832
                            ], 
                            [
                                0, 
                                1132731264
                            ], 
                            [
                                -1, 
                                2791983104
                            ]
                        ]
                    }, 
                    "roll": {
                        "__tuple__": true, 
                        "items": [
                            0, 
                            0
                        ]
                    }, 
                    "yaw": {
                        "__tuple__": true, 
                        "items": [
                            0, 
                            0
                        ]
                    }
                }
            }, 
            "entity_id": 134247451, 
            "name": "\u7d2b\u8272\u589e\u76ca", 
            "type": 64, 
            "unit_id": 186
        }, 
        "187": {
            "components": {
                "camp": {
                    "role_id": 32
                }, 
                "display": {
                    "real_scale": [
                        2.0, 
                        2.0, 
                        2.0
                    ]
                }, 
                "movement": {
                    "pitch": {
                        "__tuple__": true, 
                        "items": [
                            0, 
                            0
                        ]
                    }, 
                    "position": {
                        "__tuple__": true, 
                        "items": [
                            [
                                14, 
                                1085206528
                            ], 
                            [
                                0, 
                                585481664
                            ], 
                            [
                                -1, 
                                3683801088
                            ]
                        ]
                    }, 
                    "roll": {
                        "__tuple__": true, 
                        "items": [
                            0, 
                            0
                        ]
                    }, 
                    "yaw": {
                        "__tuple__": true, 
                        "items": [
                            0, 
                            0
                        ]
                    }
                }
            }, 
            "entity_id": 134247451, 
            "name": "\u7d2b\u8272\u589e\u76ca", 
            "type": 64, 
            "unit_id": 187
        }, 
        "188": {
            "components": {
                "camp": {
                    "role_id": 32
                }, 
                "display": {
                    "real_scale": [
                        2.0, 
                        2.0, 
                        2.0
                    ]
                }, 
                "movement": {
                    "pitch": {
                        "__tuple__": true, 
                        "items": [
                            0, 
                            0
                        ]
                    }, 
                    "position": {
                        "__tuple__": true, 
                        "items": [
                            [
                                15, 
                                1879175168
                            ], 
                            [
                                0, 
                                36471744
                            ], 
                            [
                                0, 
                                1303148544
                            ]
                        ]
                    }, 
                    "roll": {
                        "__tuple__": true, 
                        "items": [
                            0, 
                            0
                        ]
                    }, 
                    "yaw": {
                        "__tuple__": true, 
                        "items": [
                            0, 
                            0
                        ]
                    }
                }
            }, 
            "entity_id": 134247451, 
            "name": "\u7d2b\u8272\u589e\u76ca", 
            "type": 64, 
            "unit_id": 188
        }, 
        "189": {
            "components": {
                "camp": {
                    "role_id": 32
                }, 
                "display": {
                    "real_scale": [
                        2.0, 
                        2.0, 
                        2.0
                    ]
                }, 
                "movement": {
                    "pitch": {
                        "__tuple__": true, 
                        "items": [
                            0, 
                            0
                        ]
                    }, 
                    "position": {
                        "__tuple__": true, 
                        "items": [
                            [
                                16, 
                                1124401152
                            ], 
                            [
                                0, 
                                507115072
                            ], 
                            [
                                1, 
                                269613056
                            ]
                        ]
                    }, 
                    "roll": {
                        "__tuple__": true, 
                        "items": [
                            0, 
                            0
                        ]
                    }, 
                    "yaw": {
                        "__tuple__": true, 
                        "items": [
                            0, 
                            0
                        ]
                    }
                }
            }, 
            "entity_id": 134247451, 
            "name": "\u7d2b\u8272\u589e\u76ca", 
            "type": 64, 
            "unit_id": 189
        }, 
        "190": {
            "components": {
                "camp": {
                    "role_id": 32
                }, 
                "display": {
                    "real_scale": [
                        2.0, 
                        2.0, 
                        2.0
                    ]
                }, 
                "movement": {
                    "pitch": {
                        "__tuple__": true, 
                        "items": [
                            0, 
                            0
                        ]
                    }, 
                    "position": {
                        "__tuple__": true, 
                        "items": [
                            [
                                17, 
                                1397768192
                            ], 
                            [
                                0, 
                                508578944
                            ], 
                            [
                                1, 
                                2888288256
                            ]
                        ]
                    }, 
                    "roll": {
                        "__tuple__": true, 
                        "items": [
                            0, 
                            0
                        ]
                    }, 
                    "yaw": {
                        "__tuple__": true, 
                        "items": [
                            0, 
                            0
                        ]
                    }
                }
            }, 
            "entity_id": 134247451, 
            "name": "\u7d2b\u8272\u589e\u76ca", 
            "type": 64, 
            "unit_id": 190
        }, 
        "191": {
            "components": {
                "camp": {
                    "role_id": 32
                }, 
                "display": {
                    "real_scale": [
                        2.0, 
                        2.0, 
                        2.0
                    ]
                }, 
                "movement": {
                    "pitch": {
                        "__tuple__": true, 
                        "items": [
                            0, 
                            0
                        ]
                    }, 
                    "position": {
                        "__tuple__": true, 
                        "items": [
                            [
                                18, 
                                960921600
                            ], 
                            [
                                0, 
                                420047808
                            ], 
                            [
                                2, 
                                2151688192
                            ]
                        ]
                    }, 
                    "roll": {
                        "__tuple__": true, 
                        "items": [
                            0, 
                            0
                        ]
                    }, 
                    "yaw": {
                        "__tuple__": true, 
                        "items": [
                            0, 
                            0
                        ]
                    }
                }
            }, 
            "entity_id": 134247451, 
            "name": "\u7d2b\u8272\u589e\u76ca", 
            "type": 64, 
            "unit_id": 191
        }, 
        "192": {
            "components": {
                "camp": {
                    "role_id": 32
                }, 
                "display": {
                    "real_scale": [
                        2.0, 
                        2.0, 
                        2.0
                    ]
                }, 
                "movement": {
                    "pitch": {
                        "__tuple__": true, 
                        "items": [
                            0, 
                            0
                        ]
                    }, 
                    "position": {
                        "__tuple__": true, 
                        "items": [
                            [
                                18, 
                                3552804864
                            ], 
                            [
                                0, 
                                308862464
                            ], 
                            [
                                3, 
                                2044372992
                            ]
                        ]
                    }, 
                    "roll": {
                        "__tuple__": true, 
                        "items": [
                            0, 
                            0
                        ]
                    }, 
                    "yaw": {
                        "__tuple__": true, 
                        "items": [
                            0, 
                            0
                        ]
                    }
                }
            }, 
            "entity_id": 134247451, 
            "name": "\u7d2b\u8272\u589e\u76ca", 
            "type": 64, 
            "unit_id": 192
        }, 
        "193": {
            "components": {
                "camp": {
                    "role_id": 32
                }, 
                "display": {
                    "real_scale": [
                        2.0, 
                        2.0, 
                        2.0
                    ]
                }, 
                "movement": {
                    "pitch": {
                        "__tuple__": true, 
                        "items": [
                            0, 
                            0
                        ]
                    }, 
                    "position": {
                        "__tuple__": true, 
                        "items": [
                            [
                                19, 
                                371408896
                            ], 
                            [
                                0, 
                                0
                            ], 
                            [
                                4, 
                                2400356352
                            ]
                        ]
                    }, 
                    "roll": {
                        "__tuple__": true, 
                        "items": [
                            0, 
                            0
                        ]
                    }, 
                    "yaw": {
                        "__tuple__": true, 
                        "items": [
                            0, 
                            0
                        ]
                    }
                }
            }, 
            "entity_id": 134247451, 
            "name": "\u7d2b\u8272\u589e\u76ca", 
            "type": 64, 
            "unit_id": 193
        }, 
        "194": {
            "components": {
                "camp": {
                    "role_id": 32
                }, 
                "display": {
                    "real_scale": [
                        2.0, 
                        2.0, 
                        2.0
                    ]
                }, 
                "movement": {
                    "pitch": {
                        "__tuple__": true, 
                        "items": [
                            0, 
                            0
                        ]
                    }, 
                    "position": {
                        "__tuple__": true, 
                        "items": [
                            [
                                19, 
                                429424640
                            ], 
                            [
                                0, 
                                0
                            ], 
                            [
                                5, 
                                3571691520
                            ]
                        ]
                    }, 
                    "roll": {
                        "__tuple__": true, 
                        "items": [
                            0, 
                            0
                        ]
                    }, 
                    "yaw": {
                        "__tuple__": true, 
                        "items": [
                            0, 
                            0
                        ]
                    }
                }
            }, 
            "entity_id": 134247451, 
            "name": "\u7d2b\u8272\u589e\u76ca", 
            "type": 64, 
            "unit_id": 194
        }, 
        "195": {
            "components": {
                "camp": {
                    "role_id": 32
                }, 
                "display": {
                    "real_scale": [
                        2.0, 
                        2.0, 
                        2.0
                    ]
                }, 
                "movement": {
                    "pitch": {
                        "__tuple__": true, 
                        "items": [
                            0, 
                            0
                        ]
                    }, 
                    "position": {
                        "__tuple__": true, 
                        "items": [
                            [
                                18, 
                                2187984896
                            ], 
                            [
                                0, 
                                0
                            ], 
                            [
                                6, 
                                2911776768
                            ]
                        ]
                    }, 
                    "roll": {
                        "__tuple__": true, 
                        "items": [
                            0, 
                            0
                        ]
                    }, 
                    "yaw": {
                        "__tuple__": true, 
                        "items": [
                            0, 
                            0
                        ]
                    }
                }
            }, 
            "entity_id": 134247451, 
            "name": "\u7d2b\u8272\u589e\u76ca", 
            "type": 64, 
            "unit_id": 195
        }, 
        "196": {
            "components": {
                "camp": {
                    "role_id": 32
                }, 
                "display": {
                    "real_scale": [
                        2.0, 
                        2.0, 
                        2.0
                    ]
                }, 
                "movement": {
                    "pitch": {
                        "__tuple__": true, 
                        "items": [
                            0, 
                            0
                        ]
                    }, 
                    "position": {
                        "__tuple__": true, 
                        "items": [
                            [
                                17, 
                                227786752
                            ], 
                            [
                                0, 
                                10212310
                            ], 
                            [
                                7, 
                                404248576
                            ]
                        ]
                    }, 
                    "roll": {
                        "__tuple__": true, 
                        "items": [
                            0, 
                            0
                        ]
                    }, 
                    "yaw": {
                        "__tuple__": true, 
                        "items": [
                            0, 
                            0
                        ]
                    }
                }
            }, 
            "entity_id": 134247451, 
            "name": "\u7d2b\u8272\u589e\u76ca", 
            "type": 64, 
            "unit_id": 196
        }, 
        "197": {
            "components": {
                "camp": {
                    "role_id": 32
                }, 
                "display": {
                    "real_scale": [
                        2.0, 
                        2.0, 
                        2.0
                    ]
                }, 
                "movement": {
                    "pitch": {
                        "__tuple__": true, 
                        "items": [
                            0, 
                            0
                        ]
                    }, 
                    "position": {
                        "__tuple__": true, 
                        "items": [
                            [
                                15, 
                                3325710336
                            ], 
                            [
                                0, 
                                37672384
                            ], 
                            [
                                7, 
                                882118656
                            ]
                        ]
                    }, 
                    "roll": {
                        "__tuple__": true, 
                        "items": [
                            0, 
                            0
                        ]
                    }, 
                    "yaw": {
                        "__tuple__": true, 
                        "items": [
                            0, 
                            0
                        ]
                    }
                }
            }, 
            "entity_id": 134247451, 
            "name": "\u7d2b\u8272\u589e\u76ca", 
            "type": 64, 
            "unit_id": 197
        }, 
        "198": {
            "components": {
                "camp": {
                    "role_id": 32
                }, 
                "display": {
                    "real_scale": [
                        2.0, 
                        2.0, 
                        2.0
                    ]
                }, 
                "movement": {
                    "pitch": {
                        "__tuple__": true, 
                        "items": [
                            0, 
                            0
                        ]
                    }, 
                    "position": {
                        "__tuple__": true, 
                        "items": [
                            [
                                14, 
                                2706604032
                            ], 
                            [
                                0, 
                                360298944
                            ], 
                            [
                                7, 
                                908472320
                            ]
                        ]
                    }, 
                    "roll": {
                        "__tuple__": true, 
                        "items": [
                            0, 
                            0
                        ]
                    }, 
                    "yaw": {
                        "__tuple__": true, 
                        "items": [
                            0, 
                            0
                        ]
                    }
                }
            }, 
            "entity_id": 134247451, 
            "name": "\u7d2b\u8272\u589e\u76ca", 
            "type": 64, 
            "unit_id": 198
        }, 
        "199": {
            "components": {
                "camp": {
                    "role_id": 32
                }, 
                "display": {
                    "real_scale": [
                        2.0, 
                        2.0, 
                        2.0
                    ]
                }, 
                "movement": {
                    "pitch": {
                        "__tuple__": true, 
                        "items": [
                            0, 
                            0
                        ]
                    }, 
                    "position": {
                        "__tuple__": true, 
                        "items": [
                            [
                                13, 
                                1499815936
                            ], 
                            [
                                0, 
                                897176192
                            ], 
                            [
                                6, 
                                2969178112
                            ]
                        ]
                    }, 
                    "roll": {
                        "__tuple__": true, 
                        "items": [
                            0, 
                            0
                        ]
                    }, 
                    "yaw": {
                        "__tuple__": true, 
                        "items": [
                            0, 
                            0
                        ]
                    }
                }
            }, 
            "entity_id": 134247451, 
            "name": "\u7d2b\u8272\u589e\u76ca", 
            "type": 64, 
            "unit_id": 199
        }, 
        "200": {
            "components": {
                "camp": {
                    "role_id": 32
                }, 
                "display": {
                    "real_scale": [
                        2.0, 
                        2.0, 
                        2.0
                    ]
                }, 
                "movement": {
                    "pitch": {
                        "__tuple__": true, 
                        "items": [
                            0, 
                            0
                        ]
                    }, 
                    "position": {
                        "__tuple__": true, 
                        "items": [
                            [
                                12, 
                                805715968
                            ], 
                            [
                                0, 
                                1754305280
                            ], 
                            [
                                6, 
                                645320704
                            ]
                        ]
                    }, 
                    "roll": {
                        "__tuple__": true, 
                        "items": [
                            0, 
                            0
                        ]
                    }, 
                    "yaw": {
                        "__tuple__": true, 
                        "items": [
                            0, 
                            0
                        ]
                    }
                }
            }, 
            "entity_id": 134247451, 
            "name": "\u7d2b\u8272\u589e\u76ca", 
            "type": 64, 
            "unit_id": 200
        }, 
        "201": {
            "components": {
                "camp": {
                    "role_id": 32
                }, 
                "display": {
                    "real_scale": [
                        2.0, 
                        2.0, 
                        2.0
                    ]
                }, 
                "movement": {
                    "pitch": {
                        "__tuple__": true, 
                        "items": [
                            0, 
                            0
                        ]
                    }, 
                    "position": {
                        "__tuple__": true, 
                        "items": [
                            [
                                11, 
                                2393546752
                            ], 
                            [
                                0, 
                                2118964480
                            ], 
                            [
                                5, 
                                1002473472
                            ]
                        ]
                    }, 
                    "roll": {
                        "__tuple__": true, 
                        "items": [
                            0, 
                            0
                        ]
                    }, 
                    "yaw": {
                        "__tuple__": true, 
                        "items": [
                            0, 
                            0
                        ]
                    }
                }
            }, 
            "entity_id": 134247451, 
            "name": "\u7d2b\u8272\u589e\u76ca", 
            "type": 64, 
            "unit_id": 201
        }, 
        "202": {
            "components": {
                "camp": {
                    "role_id": 32
                }, 
                "display": {
                    "real_scale": [
                        2.0, 
                        2.0, 
                        2.0
                    ]
                }, 
                "movement": {
                    "pitch": {
                        "__tuple__": true, 
                        "items": [
                            0, 
                            0
                        ]
                    }, 
                    "position": {
                        "__tuple__": true, 
                        "items": [
                            [
                                12, 
                                2743214080
                            ], 
                            [
                                0, 
                                1316409088
                            ], 
                            [
                                4, 
                                3585378304
                            ]
                        ]
                    }, 
                    "roll": {
                        "__tuple__": true, 
                        "items": [
                            0, 
                            0
                        ]
                    }, 
                    "yaw": {
                        "__tuple__": true, 
                        "items": [
                            0, 
                            0
                        ]
                    }
                }
            }, 
            "entity_id": 134247451, 
            "name": "\u7d2b\u8272\u589e\u76ca", 
            "type": 64, 
            "unit_id": 202
        }, 
        "203": {
            "components": {
                "camp": {
                    "role_id": 32
                }, 
                "display": {
                    "real_scale": [
                        1.0, 
                        1.0, 
                        1.0
                    ]
                }, 
                "movement": {
                    "pitch": {
                        "__tuple__": true, 
                        "items": [
                            0, 
                            0
                        ]
                    }, 
                    "position": {
                        "__tuple__": true, 
                        "items": [
                            [
                                -6, 
                                4292796416
                            ], 
                            [
                                0, 
                                0
                            ], 
                            [
                                32, 
                                610779136
                            ]
                        ]
                    }, 
                    "roll": {
                        "__tuple__": true, 
                        "items": [
                            0, 
                            0
                        ]
                    }, 
                    "yaw": {
                        "__tuple__": true, 
                        "items": [
                            0, 
                            0
                        ]
                    }
                }
            }, 
            "entity_id": 134257943, 
            "name": "\u4f20\u9001\u95e8", 
            "type": 64, 
            "unit_id": 203
        }
    }
}