{
    "trigger_dict": {
        "18907230": {
            "action": [
                {
                    "action_type": "SET_VARIABLE", 
                    "args_list": [
                        {
                            "arg_type": 100030, 
                            "args_list": [
                                {
                                    "__tuple__": true, 
                                    "items": [
                                        "UNIT_GROUP", 
                                        "\u6682\u505c\u5355\u4f4d\u7ec4", 
                                        "local"
                                    ]
                                }
                            ], 
                            "sub_type": 1
                        }, 
                        {
                            "arg_type": 100026, 
                            "args_list": [
                                {
                                    "arg_type": 100009, 
                                    "args_list": [
                                        10062
                                    ], 
                                    "sub_type": 1
                                }
                            ], 
                            "sub_type": "AREA_UNIT_GROUP"
                        }
                    ], 
                    "bp": false, 
                    "element_id": 18907230000001, 
                    "enable": true
                }, 
                {
                    "action_type": "PICK_UNIT_DO_ACTION", 
                    "args_list": [
                        {
                            "arg_type": 100026, 
                            "args_list": [
                                {
                                    "__tuple__": true, 
                                    "items": [
                                        "UNIT_GROUP", 
                                        "\u6682\u505c\u5355\u4f4d\u7ec4", 
                                        "local"
                                    ]
                                }
                            ], 
                            "sub_type": 14
                        }, 
                        {
                            "arg_type": 100022, 
                            "args_list": [
                                {
                                    "action_type": "IF_THEN_ELSE", 
                                    "args_list": [
                                        {
                                            "arg_type": 100021, 
                                            "args_list": [
                                                {
                                                    "args_list": [
                                                        {
                                                            "arg_type": 100006, 
                                                            "args_list": [], 
                                                            "sub_type": "FOR_EACH_SELECTED_UNIT"
                                                        }, 
                                                        {
                                                            "arg_type": 100003, 
                                                            "args_list": [
                                                                {
                                                                    "__tuple__": true, 
                                                                    "items": [
                                                                        "STRING", 
                                                                        "\u5355\u4f4d\u6807\u7b7e", 
                                                                        "local"
                                                                    ]
                                                                }
                                                            ], 
                                                            "sub_type": 2
                                                        }
                                                    ], 
                                                    "condition_type": "UNIT_HAS_TAG", 
                                                    "element_id": 18907230000002, 
                                                    "enable": true
                                                }
                                            ], 
                                            "sub_type": 1
                                        }, 
                                        {
                                            "arg_type": 100022, 
                                            "args_list": [], 
                                            "sub_type": 1
                                        }, 
                                        {
                                            "arg_type": 100022, 
                                            "args_list": [
                                                {
                                                    "action_type": "REMOVE_UNIT_ENTITY_IN_GROUP", 
                                                    "args_list": [
                                                        {
                                                            "arg_type": 100026, 
                                                            "args_list": [
                                                                {
                                                                    "__tuple__": true, 
                                                                    "items": [
                                                                        "UNIT_GROUP", 
                                                                        "\u6682\u505c\u5355\u4f4d\u7ec4", 
                                                                        "local"
                                                                    ]
                                                                }
                                                            ], 
                                                            "sub_type": 14
                                                        }, 
                                                        {
                                                            "arg_type": 100006, 
                                                            "args_list": [], 
                                                            "sub_type": "FOR_EACH_SELECTED_UNIT"
                                                        }
                                                    ], 
                                                    "bp": false, 
                                                    "element_id": 18907230000003, 
                                                    "enable": true
                                                }
                                            ], 
                                            "sub_type": 1
                                        }
                                    ], 
                                    "bp": false, 
                                    "element_id": 18907230000004, 
                                    "enable": true, 
                                    "fake_op": [
                                        2
                                    ]
                                }
                            ], 
                            "sub_type": 1
                        }
                    ], 
                    "bp": false, 
                    "element_id": 18907230000005, 
                    "enable": true
                }, 
                {
                    "action_type": "PICK_UNIT_DO_ACTION", 
                    "args_list": [
                        {
                            "arg_type": 100026, 
                            "args_list": [
                                {
                                    "__tuple__": true, 
                                    "items": [
                                        "UNIT_GROUP", 
                                        "\u6682\u505c\u5355\u4f4d\u7ec4", 
                                        "local"
                                    ]
                                }
                            ], 
                            "sub_type": 14
                        }, 
                        {
                            "arg_type": 100022, 
                            "args_list": [], 
                            "sub_type": 1
                        }
                    ], 
                    "bp": false, 
                    "element_id": 18907230000007, 
                    "enable": true
                }, 
                {
                    "action_type": "PICK_UNIT_DO_ACTION", 
                    "args_list": [
                        {
                            "arg_type": 100026, 
                            "args_list": [
                                {
                                    "__tuple__": true, 
                                    "items": [
                                        "UNIT_GROUP", 
                                        "\u6682\u505c\u5355\u4f4d\u7ec4", 
                                        "local"
                                    ]
                                }
                            ], 
                            "sub_type": 14
                        }, 
                        {
                            "arg_type": 100022, 
                            "args_list": [
                                {
                                    "action_type": "CALL_TRIGGER_FUNC", 
                                    "args_list": [
                                        {
                                            "arg_type": 100177, 
                                            "args_list": [
                                                {
                                                    "arg_type": 100006, 
                                                    "args_list": [], 
                                                    "sub_type": "FOR_EACH_SELECTED_UNIT"
                                                }
                                            ], 
                                            "op_arg": [], 
                                            "op_arg_enable": [], 
                                            "sub_type": "1e7098a1812611eea02d50d63cc8db01"
                                        }
                                    ], 
                                    "bp": false, 
                                    "call_rt_arg_idxes": [], 
                                    "element_id": 18907230000042, 
                                    "enable": true
                                }
                            ], 
                            "sub_type": 1
                        }
                    ], 
                    "bp": false, 
                    "element_id": 18907230000010, 
                    "enable": true
                }
            ], 
            "call_enabled": true, 
            "condition": [], 
            "enabled": true, 
            "event": [], 
            "func_category": "t_function", 
            "func_comment": "", 
            "func_des": "\u4f7f\u5e26\u6709{\u5355\u4f4d\u6807\u7b7e}\u7684\u5355\u4f4d\u6062\u590d\u884c\u52a8", 
            "func_id": "4c830b217fc711ee824150d63cc8db01", 
            "func_name": "\u6062\u590d\u51fd\u6570", 
            "func_param_list": [
                [
                    "\u5355\u4f4d\u6807\u7b7e", 
                    true
                ]
            ], 
            "group_id": "G1HTHn-LEe6hLFDWPMjbAS", 
            "is_func": true, 
            "is_official_func": false, 
            "p_trigger_id": null, 
            "trigger_id": 18907230, 
            "trigger_name": "\u6062\u590d\u51fd\u6570", 
            "valid": true
        }, 
        "394645601": {
            "action": [
                {
                    "action_type": "IF_THEN_ELSE", 
                    "args_list": [
                        {
                            "arg_type": 100021, 
                            "args_list": [
                                {
                                    "args_list": [
                                        {
                                            "arg_type": 100000, 
                                            "args_list": [
                                                {
                                                    "arg_type": 100006, 
                                                    "args_list": [
                                                        {
                                                            "__tuple__": true, 
                                                            "items": [
                                                                "UNIT_ENTITY", 
                                                                "\u8981\u6682\u505c\u7684\u5355\u4f4d", 
                                                                "local"
                                                            ]
                                                        }
                                                    ], 
                                                    "sub_type": 11
                                                }, 
                                                {
                                                    "arg_type": 100003, 
                                                    "args_list": [
                                                        "\u6682\u505c\u524d\u79fb\u52a8\u901f\u5ea6"
                                                    ], 
                                                    "sub_type": 1
                                                }
                                            ], 
                                            "sub_type": "GET_FLOAT_KV"
                                        }, 
                                        {
                                            "arg_type": 100015, 
                                            "args_list": [
                                                "=="
                                            ], 
                                            "sub_type": 1
                                        }, 
                                        {
                                            "arg_type": 100000, 
                                            "args_list": [
                                                0.0
                                            ], 
                                            "sub_type": 1
                                        }
                                    ], 
                                    "condition_type": "FLOAT_COMPARE", 
                                    "element_id": 394645601000042, 
                                    "enable": true
                                }
                            ], 
                            "sub_type": 1
                        }, 
                        {
                            "arg_type": 100022, 
                            "args_list": [], 
                            "sub_type": 1
                        }, 
                        {
                            "arg_type": 100022, 
                            "args_list": [
                                {
                                    "action_type": "SET_ATTR", 
                                    "args_list": [
                                        {
                                            "arg_type": 100006, 
                                            "args_list": [
                                                {
                                                    "__tuple__": true, 
                                                    "items": [
                                                        "UNIT_ENTITY", 
                                                        "\u8981\u6682\u505c\u7684\u5355\u4f4d", 
                                                        "local"
                                                    ]
                                                }
                                            ], 
                                            "sub_type": 11
                                        }, 
                                        {
                                            "arg_type": 100300, 
                                            "args_list": [
                                                "ATTR_BASE"
                                            ], 
                                            "sub_type": 1
                                        }, 
                                        {
                                            "arg_type": 100042, 
                                            "args_list": [
                                                "ori_speed"
                                            ], 
                                            "sub_type": 1
                                        }, 
                                        {
                                            "arg_type": 100000, 
                                            "args_list": [
                                                {
                                                    "arg_type": 100006, 
                                                    "args_list": [
                                                        {
                                                            "__tuple__": true, 
                                                            "items": [
                                                                "UNIT_ENTITY", 
                                                                "\u8981\u6682\u505c\u7684\u5355\u4f4d", 
                                                                "local"
                                                            ]
                                                        }
                                                    ], 
                                                    "sub_type": 11
                                                }, 
                                                {
                                                    "arg_type": 100003, 
                                                    "args_list": [
                                                        "\u6682\u505c\u524d\u79fb\u52a8\u901f\u5ea6"
                                                    ], 
                                                    "sub_type": 1
                                                }
                                            ], 
                                            "sub_type": "GET_FLOAT_KV"
                                        }
                                    ], 
                                    "bp": false, 
                                    "element_id": 18907230000008, 
                                    "enable": true
                                }
                            ], 
                            "sub_type": 1
                        }
                    ], 
                    "bp": false, 
                    "element_id": 394645601000033, 
                    "enable": true, 
                    "fake_op": [
                        2
                    ]
                }, 
                {
                    "action_type": "IF_THEN_ELSE", 
                    "args_list": [
                        {
                            "arg_type": 100021, 
                            "args_list": [
                                {
                                    "args_list": [
                                        {
                                            "arg_type": 100000, 
                                            "args_list": [
                                                {
                                                    "arg_type": 100006, 
                                                    "args_list": [
                                                        [
                                                            "UNIT_ENTITY", 
                                                            "\u8981\u6682\u505c\u7684\u5355\u4f4d", 
                                                            "local"
                                                        ]
                                                    ], 
                                                    "sub_type": 11
                                                }, 
                                                {
                                                    "arg_type": 100003, 
                                                    "args_list": [
                                                        "\u6682\u505c\u524d\u653b\u51fb\u901f\u5ea6"
                                                    ], 
                                                    "sub_type": 1
                                                }
                                            ], 
                                            "sub_type": "GET_FLOAT_KV"
                                        }, 
                                        {
                                            "arg_type": 100015, 
                                            "args_list": [
                                                "=="
                                            ], 
                                            "sub_type": 1
                                        }, 
                                        {
                                            "arg_type": 100000, 
                                            "args_list": [
                                                0.0
                                            ], 
                                            "sub_type": 1
                                        }
                                    ], 
                                    "condition_type": "FLOAT_COMPARE", 
                                    "element_id": 394645601000051, 
                                    "enable": true
                                }
                            ], 
                            "sub_type": 1
                        }, 
                        {
                            "arg_type": 100022, 
                            "args_list": [], 
                            "sub_type": 1
                        }, 
                        {
                            "arg_type": 100022, 
                            "args_list": [
                                {
                                    "action_type": "SET_ATTR", 
                                    "args_list": [
                                        {
                                            "arg_type": 100006, 
                                            "args_list": [
                                                {
                                                    "__tuple__": true, 
                                                    "items": [
                                                        "UNIT_ENTITY", 
                                                        "\u8981\u6682\u505c\u7684\u5355\u4f4d", 
                                                        "local"
                                                    ]
                                                }
                                            ], 
                                            "sub_type": 11
                                        }, 
                                        {
                                            "arg_type": 100300, 
                                            "args_list": [
                                                "ATTR_BASE"
                                            ], 
                                            "sub_type": 1
                                        }, 
                                        {
                                            "arg_type": 100042, 
                                            "args_list": [
                                                "attack_speed"
                                            ], 
                                            "sub_type": 1
                                        }, 
                                        {
                                            "arg_type": 100000, 
                                            "args_list": [
                                                {
                                                    "arg_type": 100006, 
                                                    "args_list": [
                                                        {
                                                            "__tuple__": true, 
                                                            "items": [
                                                                "UNIT_ENTITY", 
                                                                "\u8981\u6682\u505c\u7684\u5355\u4f4d", 
                                                                "local"
                                                            ]
                                                        }
                                                    ], 
                                                    "sub_type": 11
                                                }, 
                                                {
                                                    "arg_type": 100003, 
                                                    "args_list": [
                                                        "\u6682\u505c\u524d\u653b\u51fb\u901f\u5ea6"
                                                    ], 
                                                    "sub_type": 1
                                                }
                                            ], 
                                            "sub_type": "GET_FLOAT_KV"
                                        }
                                    ], 
                                    "bp": false, 
                                    "element_id": 18907230000009, 
                                    "enable": true
                                }
                            ], 
                            "sub_type": 1
                        }
                    ], 
                    "bp": false, 
                    "element_id": 394645601000047, 
                    "enable": true, 
                    "fake_op": [
                        2
                    ]
                }
            ], 
            "call_enabled": true, 
            "condition": [], 
            "enabled": true, 
            "event": [], 
            "func_category": "t_function", 
            "func_comment": "", 
            "func_des": "\u8ba9{\u8981\u6682\u505c\u7684\u5355\u4f4d}\u6062\u590d", 
            "func_id": "1e7098a1812611eea02d50d63cc8db01", 
            "func_name": "\u5355\u4f4d\u6062\u590d\u51fd\u6570", 
            "func_param_list": [
                [
                    "\u8981\u6682\u505c\u7684\u5355\u4f4d", 
                    true
                ]
            ], 
            "group_id": "G1HTHn-LEe6hLFDWPMjbAS", 
            "is_func": true, 
            "is_official_func": false, 
            "p_trigger_id": null, 
            "trigger_id": 394645601, 
            "trigger_name": "\u5355\u4f4d\u6062\u590d\u51fd\u6570", 
            "valid": true
        }, 
        "589332573": {
            "action": [
                {
                    "action_type": "SET_VARIABLE", 
                    "args_list": [
                        {
                            "arg_type": 100030, 
                            "args_list": [
                                {
                                    "__tuple__": true, 
                                    "items": [
                                        "UNIT_GROUP", 
                                        "\u6682\u505c\u5355\u4f4d\u7ec4", 
                                        "local"
                                    ]
                                }
                            ], 
                            "sub_type": 1
                        }, 
                        {
                            "arg_type": 100026, 
                            "args_list": [
                                {
                                    "arg_type": 100009, 
                                    "args_list": [
                                        10062
                                    ], 
                                    "sub_type": 1
                                }
                            ], 
                            "sub_type": "AREA_UNIT_GROUP"
                        }
                    ], 
                    "bp": false, 
                    "element_id": 589332573000001, 
                    "enable": true
                }, 
                {
                    "action_type": "PICK_UNIT_DO_ACTION", 
                    "args_list": [
                        {
                            "arg_type": 100026, 
                            "args_list": [
                                {
                                    "__tuple__": true, 
                                    "items": [
                                        "UNIT_GROUP", 
                                        "\u6682\u505c\u5355\u4f4d\u7ec4", 
                                        "local"
                                    ]
                                }
                            ], 
                            "sub_type": 14
                        }, 
                        {
                            "arg_type": 100022, 
                            "args_list": [
                                {
                                    "action_type": "IF_THEN_ELSE", 
                                    "args_list": [
                                        {
                                            "arg_type": 100021, 
                                            "args_list": [
                                                {
                                                    "args_list": [
                                                        {
                                                            "arg_type": 100006, 
                                                            "args_list": [], 
                                                            "sub_type": "FOR_EACH_SELECTED_UNIT"
                                                        }, 
                                                        {
                                                            "arg_type": 100003, 
                                                            "args_list": [
                                                                {
                                                                    "__tuple__": true, 
                                                                    "items": [
                                                                        "STRING", 
                                                                        "\u5355\u4f4d\u6807\u7b7e", 
                                                                        "local"
                                                                    ]
                                                                }
                                                            ], 
                                                            "sub_type": 2
                                                        }
                                                    ], 
                                                    "condition_type": "UNIT_HAS_TAG", 
                                                    "element_id": 589332573000002, 
                                                    "enable": true
                                                }
                                            ], 
                                            "sub_type": 1
                                        }, 
                                        {
                                            "arg_type": 100022, 
                                            "args_list": [], 
                                            "sub_type": 1
                                        }, 
                                        {
                                            "arg_type": 100022, 
                                            "args_list": [
                                                {
                                                    "action_type": "REMOVE_UNIT_ENTITY_IN_GROUP", 
                                                    "args_list": [
                                                        {
                                                            "arg_type": 100026, 
                                                            "args_list": [
                                                                {
                                                                    "__tuple__": true, 
                                                                    "items": [
                                                                        "UNIT_GROUP", 
                                                                        "\u6682\u505c\u5355\u4f4d\u7ec4", 
                                                                        "local"
                                                                    ]
                                                                }
                                                            ], 
                                                            "sub_type": 14
                                                        }, 
                                                        {
                                                            "arg_type": 100006, 
                                                            "args_list": [], 
                                                            "sub_type": "FOR_EACH_SELECTED_UNIT"
                                                        }
                                                    ], 
                                                    "bp": false, 
                                                    "element_id": 589332573000003, 
                                                    "enable": true
                                                }
                                            ], 
                                            "sub_type": 1
                                        }
                                    ], 
                                    "bp": false, 
                                    "element_id": 589332573000004, 
                                    "enable": true, 
                                    "fake_op": [
                                        2
                                    ]
                                }
                            ], 
                            "sub_type": 1
                        }
                    ], 
                    "bp": false, 
                    "element_id": 589332573000005, 
                    "enable": true
                }, 
                {
                    "action_type": "PICK_UNIT_DO_ACTION", 
                    "args_list": [
                        {
                            "arg_type": 100026, 
                            "args_list": [
                                {
                                    "__tuple__": true, 
                                    "items": [
                                        "UNIT_GROUP", 
                                        "\u6682\u505c\u5355\u4f4d\u7ec4", 
                                        "local"
                                    ]
                                }
                            ], 
                            "sub_type": 14
                        }, 
                        {
                            "arg_type": 100022, 
                            "args_list": [], 
                            "sub_type": 1
                        }
                    ], 
                    "bp": false, 
                    "element_id": 589332573000007, 
                    "enable": true
                }, 
                {
                    "action_type": "PICK_UNIT_DO_ACTION", 
                    "args_list": [
                        {
                            "arg_type": 100026, 
                            "args_list": [
                                {
                                    "__tuple__": true, 
                                    "items": [
                                        "UNIT_GROUP", 
                                        "\u6682\u505c\u5355\u4f4d\u7ec4", 
                                        "local"
                                    ]
                                }
                            ], 
                            "sub_type": 14
                        }, 
                        {
                            "arg_type": 100022, 
                            "args_list": [
                                {
                                    "action_type": "CALL_TRIGGER_FUNC", 
                                    "args_list": [
                                        {
                                            "arg_type": 100177, 
                                            "args_list": [
                                                {
                                                    "arg_type": 100006, 
                                                    "args_list": [], 
                                                    "sub_type": "FOR_EACH_SELECTED_UNIT"
                                                }
                                            ], 
                                            "op_arg": [], 
                                            "op_arg_enable": [], 
                                            "sub_type": "ccd22040812511eea0fe50d63cc8db01"
                                        }
                                    ], 
                                    "bp": false, 
                                    "call_rt_arg_idxes": [], 
                                    "element_id": 589332573000018, 
                                    "enable": true
                                }
                            ], 
                            "sub_type": 1
                        }
                    ], 
                    "bp": false, 
                    "element_id": 589332573000012, 
                    "enable": true
                }
            ], 
            "call_enabled": true, 
            "condition": [], 
            "enabled": true, 
            "event": [], 
            "func_category": "t_function", 
            "func_comment": "", 
            "func_des": "\u4f7f\u5e26\u6709{\u5355\u4f4d\u6807\u7b7e}\u7684\u5355\u4f4d\u505c\u6b62\u884c\u52a8", 
            "func_id": "491aac707fbf11ee890e50d63cc8db01", 
            "func_name": "\u6682\u505c\u51fd\u6570", 
            "func_param_list": [
                {
                    "__tuple__": true, 
                    "items": [
                        "\u5355\u4f4d\u6807\u7b7e", 
                        true
                    ]
                }
            ], 
            "group_id": "G1HTHn-LEe6hLFDWPMjbAS", 
            "is_func": true, 
            "is_official_func": false, 
            "p_trigger_id": null, 
            "trigger_id": 589332573, 
            "trigger_name": "\u6682\u505c\u51fd\u6570", 
            "valid": true
        }, 
        "779456611": {
            "action": [
                {
                    "action_type": "SET_VARIABLE", 
                    "args_list": [
                        {
                            "arg_type": 100030, 
                            "args_list": [
                                [
                                    "STRING", 
                                    "\u6e38\u620f\u6682\u505cor\u8fdb\u884c"
                                ]
                            ], 
                            "sub_type": 1
                        }, 
                        {
                            "arg_type": 100003, 
                            "args_list": [
                                "\u6682\u505c"
                            ], 
                            "sub_type": 1
                        }
                    ], 
                    "bp": false, 
                    "element_id": 779456611000001, 
                    "enable": true
                }, 
                {
                    "action_type": "CALL_TRIGGER_FUNC", 
                    "args_list": [
                        {
                            "arg_type": 100177, 
                            "args_list": [
                                {
                                    "arg_type": 100003, 
                                    "args_list": [
                                        "\u602a\u7269"
                                    ], 
                                    "sub_type": 1
                                }
                            ], 
                            "op_arg": [], 
                            "op_arg_enable": [], 
                            "sub_type": "491aac707fbf11ee890e50d63cc8db01"
                        }
                    ], 
                    "bp": false, 
                    "call_rt_arg_idxes": [], 
                    "element_id": 1390952533000170, 
                    "enable": true
                }, 
                {
                    "action_type": "CALL_TRIGGER_FUNC", 
                    "args_list": [
                        {
                            "arg_type": 100177, 
                            "args_list": [
                                {
                                    "arg_type": 100003, 
                                    "args_list": [
                                        "\u9632\u5fa1\u5854"
                                    ], 
                                    "sub_type": 1
                                }
                            ], 
                            "op_arg": [], 
                            "op_arg_enable": [], 
                            "sub_type": "491aac707fbf11ee890e50d63cc8db01"
                        }
                    ], 
                    "bp": false, 
                    "call_rt_arg_idxes": [], 
                    "element_id": 1390952533000176, 
                    "enable": true
                }
            ], 
            "call_enabled": true, 
            "condition": [], 
            "enabled": true, 
            "event": [], 
            "func_category": "t_function", 
            "func_comment": "", 
            "func_des": "\u602a\u7269\u3001\u9632\u5fa1\u5854\u505c\u6b62\u884c\u52a8", 
            "func_id": "0c2966f0812f11eeb37750d63cc8db01", 
            "func_name": "\u6e38\u620f\u6682\u505c", 
            "group_id": "G1HTHn-LEe6hLFDWPMjbAS", 
            "is_func": true, 
            "is_official_func": false, 
            "p_trigger_id": null, 
            "trigger_id": 779456611, 
            "trigger_name": "\u6e38\u620f\u6682\u505c", 
            "valid": true
        }, 
        "1434271840": {
            "action": [
                {
                    "action_type": "IF_THEN_ELSE", 
                    "args_list": [
                        {
                            "arg_type": 100021, 
                            "args_list": [
                                {
                                    "args_list": [
                                        {
                                            "arg_type": 100000, 
                                            "args_list": [
                                                {
                                                    "arg_type": 100006, 
                                                    "args_list": [
                                                        {
                                                            "__tuple__": true, 
                                                            "items": [
                                                                "UNIT_ENTITY", 
                                                                "\u8981\u6682\u505c\u7684\u5355\u4f4d", 
                                                                "local"
                                                            ]
                                                        }
                                                    ], 
                                                    "sub_type": 11
                                                }, 
                                                {
                                                    "arg_type": 100301, 
                                                    "args_list": [
                                                        "ATTR_BASE"
                                                    ], 
                                                    "sub_type": 1
                                                }, 
                                                {
                                                    "arg_type": 100042, 
                                                    "args_list": [
                                                        "ori_speed"
                                                    ], 
                                                    "sub_type": 1
                                                }
                                            ], 
                                            "sub_type": "GET_UNIT_ATTR"
                                        }, 
                                        {
                                            "arg_type": 100015, 
                                            "args_list": [
                                                "=="
                                            ], 
                                            "sub_type": 1
                                        }, 
                                        {
                                            "arg_type": 100000, 
                                            "args_list": [
                                                0.0
                                            ], 
                                            "sub_type": 1
                                        }
                                    ], 
                                    "condition_type": "FLOAT_COMPARE", 
                                    "element_id": 1434271840000062, 
                                    "enable": true
                                }
                            ], 
                            "sub_type": 1
                        }, 
                        {
                            "arg_type": 100022, 
                            "args_list": [], 
                            "sub_type": 1
                        }, 
                        {
                            "arg_type": 100022, 
                            "args_list": [
                                {
                                    "action_type": "SET_ENTITY_KV", 
                                    "args_list": [
                                        {
                                            "arg_type": 100006, 
                                            "args_list": [
                                                {
                                                    "__tuple__": true, 
                                                    "items": [
                                                        "UNIT_ENTITY", 
                                                        "\u8981\u6682\u505c\u7684\u5355\u4f4d", 
                                                        "local"
                                                    ]
                                                }
                                            ], 
                                            "sub_type": 11
                                        }, 
                                        {
                                            "arg_type": 100003, 
                                            "args_list": [
                                                "\u6682\u505c\u524d\u79fb\u52a8\u901f\u5ea6"
                                            ], 
                                            "sub_type": 1
                                        }, 
                                        {
                                            "arg_type": 100000, 
                                            "args_list": [
                                                {
                                                    "arg_type": 100006, 
                                                    "args_list": [
                                                        {
                                                            "__tuple__": true, 
                                                            "items": [
                                                                "UNIT_ENTITY", 
                                                                "\u8981\u6682\u505c\u7684\u5355\u4f4d", 
                                                                "local"
                                                            ]
                                                        }
                                                    ], 
                                                    "sub_type": 11
                                                }, 
                                                {
                                                    "arg_type": 100301, 
                                                    "args_list": [
                                                        "ATTR_BASE"
                                                    ], 
                                                    "sub_type": 1
                                                }, 
                                                {
                                                    "arg_type": 100042, 
                                                    "args_list": [
                                                        "ori_speed"
                                                    ], 
                                                    "sub_type": 1
                                                }
                                            ], 
                                            "sub_type": "GET_UNIT_ATTR"
                                        }
                                    ], 
                                    "bp": false, 
                                    "element_id": 589332573000008, 
                                    "enable": true
                                }, 
                                {
                                    "action_type": "SET_ATTR", 
                                    "args_list": [
                                        {
                                            "arg_type": 100006, 
                                            "args_list": [
                                                {
                                                    "__tuple__": true, 
                                                    "items": [
                                                        "UNIT_ENTITY", 
                                                        "\u8981\u6682\u505c\u7684\u5355\u4f4d", 
                                                        "local"
                                                    ]
                                                }
                                            ], 
                                            "sub_type": 11
                                        }, 
                                        {
                                            "arg_type": 100300, 
                                            "args_list": [
                                                "ATTR_BASE"
                                            ], 
                                            "sub_type": 1
                                        }, 
                                        {
                                            "arg_type": 100042, 
                                            "args_list": [
                                                "ori_speed"
                                            ], 
                                            "sub_type": 1
                                        }, 
                                        {
                                            "arg_type": 100000, 
                                            "args_list": [
                                                0.0
                                            ], 
                                            "sub_type": 1
                                        }
                                    ], 
                                    "bp": false, 
                                    "element_id": 589332573000009, 
                                    "enable": true
                                }
                            ], 
                            "sub_type": 1
                        }
                    ], 
                    "bp": false, 
                    "element_id": 1434271840000052, 
                    "enable": true, 
                    "fake_op": [
                        2
                    ]
                }, 
                {
                    "action_type": "IF_THEN_ELSE", 
                    "args_list": [
                        {
                            "arg_type": 100021, 
                            "args_list": [
                                {
                                    "args_list": [
                                        {
                                            "arg_type": 100000, 
                                            "args_list": [
                                                {
                                                    "arg_type": 100006, 
                                                    "args_list": [
                                                        [
                                                            "UNIT_ENTITY", 
                                                            "\u8981\u6682\u505c\u7684\u5355\u4f4d", 
                                                            "local"
                                                        ]
                                                    ], 
                                                    "sub_type": 11
                                                }, 
                                                {
                                                    "arg_type": 100301, 
                                                    "args_list": [
                                                        "ATTR_BASE"
                                                    ], 
                                                    "sub_type": 1
                                                }, 
                                                {
                                                    "arg_type": 100042, 
                                                    "args_list": [
                                                        "attack_speed"
                                                    ], 
                                                    "sub_type": 1
                                                }
                                            ], 
                                            "sub_type": "GET_UNIT_ATTR"
                                        }, 
                                        {
                                            "arg_type": 100015, 
                                            "args_list": [
                                                "=="
                                            ], 
                                            "sub_type": 1
                                        }, 
                                        {
                                            "arg_type": 100000, 
                                            "args_list": [
                                                0.0
                                            ], 
                                            "sub_type": 1
                                        }
                                    ], 
                                    "condition_type": "FLOAT_COMPARE", 
                                    "element_id": 1434271840000071, 
                                    "enable": true
                                }
                            ], 
                            "sub_type": 1
                        }, 
                        {
                            "arg_type": 100022, 
                            "args_list": [], 
                            "sub_type": 1
                        }, 
                        {
                            "arg_type": 100022, 
                            "args_list": [
                                {
                                    "action_type": "SET_ENTITY_KV", 
                                    "args_list": [
                                        {
                                            "arg_type": 100006, 
                                            "args_list": [
                                                [
                                                    "UNIT_ENTITY", 
                                                    "\u8981\u6682\u505c\u7684\u5355\u4f4d", 
                                                    "local"
                                                ]
                                            ], 
                                            "sub_type": 11
                                        }, 
                                        {
                                            "arg_type": 100003, 
                                            "args_list": [
                                                "\u6682\u505c\u524d\u653b\u51fb\u901f\u5ea6"
                                            ], 
                                            "sub_type": 1
                                        }, 
                                        {
                                            "arg_type": 100000, 
                                            "args_list": [
                                                {
                                                    "arg_type": 100006, 
                                                    "args_list": [
                                                        [
                                                            "UNIT_ENTITY", 
                                                            "\u8981\u6682\u505c\u7684\u5355\u4f4d", 
                                                            "local"
                                                        ]
                                                    ], 
                                                    "sub_type": 11
                                                }, 
                                                {
                                                    "arg_type": 100301, 
                                                    "args_list": [
                                                        "ATTR_BASE"
                                                    ], 
                                                    "sub_type": 1
                                                }, 
                                                {
                                                    "arg_type": 100042, 
                                                    "args_list": [
                                                        "attack_speed"
                                                    ], 
                                                    "sub_type": 1
                                                }
                                            ], 
                                            "sub_type": "GET_UNIT_ATTR"
                                        }
                                    ], 
                                    "bp": false, 
                                    "element_id": 1434271840000089, 
                                    "enable": true
                                }, 
                                {
                                    "action_type": "SET_ATTR", 
                                    "args_list": [
                                        {
                                            "arg_type": 100006, 
                                            "args_list": [
                                                [
                                                    "UNIT_ENTITY", 
                                                    "\u8981\u6682\u505c\u7684\u5355\u4f4d", 
                                                    "local"
                                                ]
                                            ], 
                                            "sub_type": 11
                                        }, 
                                        {
                                            "arg_type": 100300, 
                                            "args_list": [
                                                "ATTR_BASE"
                                            ], 
                                            "sub_type": 1
                                        }, 
                                        {
                                            "arg_type": 100042, 
                                            "args_list": [
                                                "attack_speed"
                                            ], 
                                            "sub_type": 1
                                        }, 
                                        {
                                            "arg_type": 100000, 
                                            "args_list": [
                                                0.0
                                            ], 
                                            "sub_type": 1
                                        }
                                    ], 
                                    "bp": false, 
                                    "element_id": 1434271840000103, 
                                    "enable": true
                                }
                            ], 
                            "sub_type": 1
                        }
                    ], 
                    "bp": false, 
                    "element_id": 1434271840000067, 
                    "enable": true, 
                    "fake_op": [
                        2
                    ]
                }
            ], 
            "call_enabled": true, 
            "condition": [], 
            "enabled": true, 
            "event": [], 
            "func_category": "t_function", 
            "func_comment": "", 
            "func_des": "\u8ba9{\u8981\u6682\u505c\u7684\u5355\u4f4d}\u6682\u505c", 
            "func_id": "ccd22040812511eea0fe50d63cc8db01", 
            "func_name": "\u5355\u4f4d\u6682\u505c\u51fd\u6570", 
            "func_param_list": [
                {
                    "__tuple__": true, 
                    "items": [
                        "\u8981\u6682\u505c\u7684\u5355\u4f4d", 
                        true
                    ]
                }
            ], 
            "group_id": "G1HTHn-LEe6hLFDWPMjbAS", 
            "is_func": true, 
            "is_official_func": false, 
            "p_trigger_id": null, 
            "trigger_id": 1434271840, 
            "trigger_name": "\u5355\u4f4d\u6682\u505c\u51fd\u6570", 
            "valid": true
        }, 
        "1785892962": {
            "action": [
                {
                    "action_type": "SET_VARIABLE", 
                    "args_list": [
                        {
                            "arg_type": 100030, 
                            "args_list": [
                                {
                                    "__tuple__": true, 
                                    "items": [
                                        "STRING", 
                                        "\u6e38\u620f\u6682\u505cor\u8fdb\u884c"
                                    ]
                                }
                            ], 
                            "sub_type": 1
                        }, 
                        {
                            "arg_type": 100003, 
                            "args_list": [
                                "\u8fdb\u884c"
                            ], 
                            "sub_type": 1
                        }
                    ], 
                    "bp": false, 
                    "element_id": 1785892962000003, 
                    "enable": true
                }, 
                {
                    "action_type": "CALL_TRIGGER_FUNC", 
                    "args_list": [
                        {
                            "arg_type": 100177, 
                            "args_list": [
                                {
                                    "arg_type": 100003, 
                                    "args_list": [
                                        "\u602a\u7269"
                                    ], 
                                    "sub_type": 1
                                }
                            ], 
                            "op_arg": [], 
                            "op_arg_enable": [], 
                            "sub_type": "4c830b217fc711ee824150d63cc8db01"
                        }
                    ], 
                    "bp": false, 
                    "call_rt_arg_idxes": [], 
                    "element_id": 1363304534000056, 
                    "enable": true
                }, 
                {
                    "action_type": "CALL_TRIGGER_FUNC", 
                    "args_list": [
                        {
                            "arg_type": 100177, 
                            "args_list": [
                                {
                                    "arg_type": 100003, 
                                    "args_list": [
                                        "\u9632\u5fa1\u5854"
                                    ], 
                                    "sub_type": 1
                                }
                            ], 
                            "op_arg": [], 
                            "op_arg_enable": [], 
                            "sub_type": "4c830b217fc711ee824150d63cc8db01"
                        }
                    ], 
                    "bp": false, 
                    "call_rt_arg_idxes": [], 
                    "element_id": 1363304534000062, 
                    "enable": false
                }
            ], 
            "call_enabled": true, 
            "condition": [], 
            "enabled": true, 
            "event": [], 
            "func_category": "t_function", 
            "func_comment": "", 
            "func_des": "\u602a\u7269\u6062\u590d\u884c\u52a8", 
            "func_id": "ef67f3ae812e11eebda050d63cc8db01", 
            "func_name": "\u6e38\u620f\u8fdb\u884c", 
            "group_id": "G1HTHn-LEe6hLFDWPMjbAS", 
            "is_func": true, 
            "is_official_func": false, 
            "p_trigger_id": null, 
            "trigger_id": 1785892962, 
            "trigger_name": "\u6e38\u620f\u8fdb\u884c", 
            "valid": true
        }
    }, 
    "trigger_group_info": {
        "_function_": true, 
        "_trigger_group_": true, 
        "group": [
            {
                "__tuple__": true, 
                "items": [
                    589332573, 
                    "\u6682\u505c\u51fd\u6570"
                ]
            }, 
            {
                "__tuple__": true, 
                "items": [
                    1434271840, 
                    "\u5355\u4f4d\u6682\u505c\u51fd\u6570"
                ]
            }, 
            {
                "__tuple__": true, 
                "items": [
                    18907230, 
                    "\u6062\u590d\u51fd\u6570"
                ]
            }, 
            {
                "__tuple__": true, 
                "items": [
                    394645601, 
                    "\u5355\u4f4d\u6062\u590d\u51fd\u6570"
                ]
            }, 
            {
                "__tuple__": true, 
                "items": [
                    1785892962, 
                    "\u6e38\u620f\u8fdb\u884c"
                ]
            }, 
            {
                "__tuple__": true, 
                "items": [
                    779456611, 
                    "\u6e38\u620f\u6682\u505c"
                ]
            }
        ], 
        "is_sub_folder": false, 
        "key": "G1HTHn-LEe6hLFDWPMjbAS", 
        "name": "\u6682\u505c"
    }
}